SpotToQob/SpotToQob.py
SpotToQob/__init__.py
SpotToQob-1.0.2.dist-info/LICENSE
SpotToQob-1.0.2.dist-info/METADATA
SpotToQob-1.0.2.dist-info/WHEEL
SpotToQob-1.0.2.dist-info/entry_points.txt
SpotToQob-1.0.2.dist-info/top_level.txt
SpotToQob-1.0.2.dist-info/RECORD
