Metadata-Version: 2.1
Name: SpotToQob
Version: 1.0.2
Summary: Backup a CSV or Spotify playlist URL using Qobuz-dl
Home-page: https://github.com/BrendanStupik/SpotToQob
Author: Brendan Stupik
Author-email: spottoqob@brendanstupik.anonaddy.com
License: MIT
Platform: UNKNOWN
License-File: LICENSE
Requires-Dist: configparser (>=5.0.0)
Requires-Dist: pandas (>=1.0.0)
Requires-Dist: qobuz-dl (>=0.9.9.10)
Requires-Dist: spotipy (>=2.0.0)
